{
  "image": "study_proof_noise_gaussian.png",
  "doc_type": "study_proof",
  "variant": {
    "type": "noise",
    "method": "gaussian",
    "sigma": 5
  },
  "generated_at": "2026-07-14T15:44:00.768811",
  "ground_truth": {
    "name": "李丽芳",
    "gender": "女",
    "id_number": "310110198106155674",
    "birth_date": "1981-06-15",
    "university": "南京大学",
    "major": "护理学",
    "level": "本科",
    "start_date": "2006-09-01",
    "expected_graduation": "2010-06-30",
    "student_no": "2006056093",
    "status": "在读"
  },
  "image_size": {
    "width": 1240,
    "height": 1754
  }
}